Metadata-Version: 1.0
Name: finwic
Version: 0.1
Summary: Creates a word cloud from filenames
Home-page: https://github.com/lawrencehlee/finwic
Author: Lawrence H Lee
Author-email: Lee.LawrenceH@gmail.com
License: MIT
Platform: UNKNOWN
